fsub/__init__.py
fsub/fsub.py
fsub-1.0.4.dist-info/LICENSE
fsub-1.0.4.dist-info/METADATA
fsub-1.0.4.dist-info/WHEEL
fsub-1.0.4.dist-info/entry_points.txt
fsub-1.0.4.dist-info/top_level.txt
fsub-1.0.4.dist-info/RECORD
