Metadata-Version: 2.1
Name: fsub
Version: 1.0.4
Summary: CLI SubRip editor
Home-page: https://github.com/augustogunsch/fsub
Author: Augusto Lenz Gunsch
Author-email: augustogunsch@tutanota.com
License: UNKNOWN
Project-URL: Bug Tracker, https://github.com/augustogunsch/fsub/issues
Platform: UNKNOWN
Classifier: Programming Language :: Python :: 3
Classifier: License :: OSI Approved :: GNU General Public License v3 (GPLv3)
Classifier: Operating System :: OS Independent
Classifier: Development Status :: 6 - Mature
Classifier: Topic :: Terminals
Classifier: Topic :: Text Processing :: General
Classifier: Topic :: Text Processing :: Filters
Classifier: Topic :: Utilities
Requires-Python: >=3.9
License-File: LICENSE
Requires-Dist: chardet
